impersonation/__init__.py
impersonation/core.py
impersonation/utils.py
impersonation-1.1.0.dist-info/LICENSE
impersonation-1.1.0.dist-info/METADATA
impersonation-1.1.0.dist-info/WHEEL
impersonation-1.1.0.dist-info/RECORD
