Metadata-Version: 2.1
Name: impersonation
Version: 1.1.0
Summary: Utility for user impersonation by running instructions under given user
Home-page: https://github.com/codectl/impersonation
License: MIT
Keywords: process,multiprocessing,impersonate,python,python3
Author: Renato Damas
Author-email: rena2damas@gmail.com
Requires-Python: >=3.8,<4.0
Classifier: Intended Audience :: Developers
Classifier: License :: OSI Approved :: MIT License
Classifier: Natural Language :: English
Classifier: Programming Language :: Python :: 3
Classifier: Programming Language :: Python :: 3.8
Classifier: Programming Language :: Python :: 3.9
Classifier: Programming Language :: Python :: 3.10
Classifier: Programming Language :: Python :: 3.11
Classifier: Programming Language :: Python :: 3
Classifier: Programming Language :: Python :: 3.10
Classifier: Programming Language :: Python :: 3.11
Classifier: Programming Language :: Python :: 3.8
Classifier: Programming Language :: Python :: 3.9
Project-URL: Repository, https://github.com/codectl/impersonation
Project-URL: issues, https://github.com/codectl/impersonation/issues
